feedsearch/__init__.py
feedsearch/__version__.py
feedsearch/feedfinder.py
feedsearch/feedinfo.py
feedsearch/feedsearch.py
feedsearch/lib.py
feedsearch/site_meta.py
feedsearch/url.py
feedsearch-1.0.12.dist-info/LICENSE
feedsearch-1.0.12.dist-info/METADATA
feedsearch-1.0.12.dist-info/WHEEL
feedsearch-1.0.12.dist-info/top_level.txt
feedsearch-1.0.12.dist-info/RECORD
