Metadata-Version: 2.1
Name: feedsearch
Version: 1.0.12
Summary: Search sites for RSS, Atom, and JSON feeds
Home-page: https://github.com/DBeath/feedsearch
Author: David Beath
Author-email: davidgbeath@gmail.com
License: MIT
Platform: UNKNOWN
Classifier: License :: OSI Approved :: MIT License
Classifier: Intended Audience :: Developers
Classifier: Development Status :: 5 - Production/Stable
Classifier: Natural Language :: English
Classifier: Operating System :: OS Independent
Classifier: Programming Language :: Python :: 3.5
Classifier: Programming Language :: Python :: 3.6
Classifier: Programming Language :: Python :: 3.7
Requires-Python: >=3
Requires-Dist: requests
Requires-Dist: beautifulsoup4
Requires-Dist: feedparser
Requires-Dist: click
Requires-Dist: Werkzeug
